{
  "objects": [
    {
      "type": "Cylinder",
      "position": {
        "radius": 30,
        "angle": 0,
        "height": 0
      },
      "material":"Black",
      "scale": {
        "x": 5.25,
        "y": 100,
        "z": 5.25
      },
      "flip": false
    },
    {
      "type": "Cylinder",
      "position": {
        "radius": 0,
        "angle": 0,
        "height": -5.5
      },
      "material": "Black",
      "scale": {
        "x": 15,
        "y": 1,
        "z": 15
      }
    },
    {
      "type": "Cylinder",
      "position": {
        "radius": 0,
        "angle": 0,
        "height": 5.5
      },
      "material": "Black",
      "scale": {
        "x": 15,
        "y": 1,
        "z": 15
      }
    }
  ],
  "closedLoopOrientation": true,
  "closedLoopPosition": false,
  "backgroundColor": {
    "r": 0.8,
    "g": 0.8,
    "b": 0.8,
    "a": 1
  }
}
