{
  "seed": -1,
  "repetitions": 10,
  "sync": true,
  "intertrial": {
    "name": "skybox",
    "trigger": {
      "type": "time",
      "seconds": 15
    },
      "objects": [
        {
          "type": "glassplane",
          "polar": {
            "radius": 0,
            "angle": 0,
            "height": -1
          }
        }
      ],
    "camera": [
      {
        "vrId": "VR1",
        "clearFlags": "Skybox"
      },
      {
        "vrId": "VR2",
        "clearFlags": "Skybox"
      },
      {
        "vrId": "VR3",
        "clearFlags": "Skybox"
      },
      {
        "vrId": "VR4",
        "clearFlags": "Skybox"
      }
    ]
  },
  "steps": [
    {
      "name": "ScalingChoice_Blue_BlueGreen_20deg",
      "trigger": {
        "type": "time",
        "seconds": 45
      },
      "closedLoopOrientation": true,
      "closedLoopPosition": true,
      "objects": [
        {
          "type": "ScalingCylinder",
          "polar": {
            "radius": 60,
            "angle": -10.0,
            "height": 0
          },
          "material": "Blue",
          "scale": {
            "x": 7,
            "y": 100,
            "z": 7
          },
          "visualAngleDegrees": 10
        },
        {
          "type": "ScalingCylinder",
          "polar": {
            "radius": 60,
            "angle": 10.0,
            "height": 0
          },
          "material": "BlueGreen",
          "scale": {
            "x": 7,
            "y": 100,
            "z": 7
          },
          "visualAngleDegrees": 10
        }
      ],
      "camera": [
        {
          "vrId": "VR1",
          "clearFlags": "SolidColor",
          "bgColor": [
            0.8,
            0.8,
            0.8,
            1.0
          ]
        },
        {
          "vrId": "VR2",
          "clearFlags": "SolidColor",
          "bgColor": [
            0.8,
            0.8,
            0.8,
            1.0
          ]
        },
        {
          "vrId": "VR3",
          "clearFlags": "SolidColor",
          "bgColor": [
            0.8,
            0.8,
            0.8,
            1.0
          ]
        },
        {
          "vrId": "VR4",
          "clearFlags": "SolidColor",
          "bgColor": [
            0.8,
            0.8,
            0.8,
            1.0
          ]
        }
      ]
    },
    {
      "name": "ScalingChoice_BlueGreen_Blue_20deg",
      "trigger": {
        "type": "time",
        "seconds": 45
      },
      "closedLoopOrientation": true,
      "closedLoopPosition": true,
      "objects": [
        {
          "type": "ScalingCylinder",
          "polar": {
            "radius": 60,
            "angle": -10.0,
            "height": 0
          },
          "material": "BlueGreen",
          "scale": {
            "x": 7,
            "y": 100,
            "z": 7
          },
          "visualAngleDegrees": 10
        },
        {
          "type": "ScalingCylinder",
          "polar": {
            "radius": 60,
            "angle": 10.0,
            "height": 0
          },
          "material": "Blue",
          "scale": {
            "x": 7,
            "y": 100,
            "z": 7
          },
          "visualAngleDegrees": 10
        }
      ],
      "camera": [
        {
          "vrId": "VR1",
          "clearFlags": "SolidColor",
          "bgColor": [
            0.8,
            0.8,
            0.8,
            1.0
          ]
        },
        {
          "vrId": "VR2",
          "clearFlags": "SolidColor",
          "bgColor": [
            0.8,
            0.8,
            0.8,
            1.0
          ]
        },
        {
          "vrId": "VR3",
          "clearFlags": "SolidColor",
          "bgColor": [
            0.8,
            0.8,
            0.8,
            1.0
          ]
        },
        {
          "vrId": "VR4",
          "clearFlags": "SolidColor",
          "bgColor": [
            0.8,
            0.8,
            0.8,
            1.0
          ]
        }
      ]
    },
    {
      "name": "ScalingChoice_Blue_BlueGreen_30deg",
      "trigger": {
        "type": "time",
        "seconds": 45
      },
      "closedLoopOrientation": true,
      "closedLoopPosition": true,
      "objects": [
        {
          "type": "ScalingCylinder",
          "polar": {
            "radius": 60,
            "angle": -15.0,
            "height": 0
          },
          "material": "Blue",
          "scale": {
            "x": 7,
            "y": 100,
            "z": 7
          },
          "visualAngleDegrees": 10
        },
        {
          "type": "ScalingCylinder",
          "polar": {
            "radius": 60,
            "angle": 15.0,
            "height": 0
          },
          "material": "BlueGreen",
          "scale": {
            "x": 7,
            "y": 100,
            "z": 7
          },
          "visualAngleDegrees": 10
        }
      ],
      "camera": [
        {
          "vrId": "VR1",
          "clearFlags": "SolidColor",
          "bgColor": [
            0.8,
            0.8,
            0.8,
            1.0
          ]
        },
        {
          "vrId": "VR2",
          "clearFlags": "SolidColor",
          "bgColor": [
            0.8,
            0.8,
            0.8,
            1.0
          ]
        },
        {
          "vrId": "VR3",
          "clearFlags": "SolidColor",
          "bgColor": [
            0.8,
            0.8,
            0.8,
            1.0
          ]
        },
        {
          "vrId": "VR4",
          "clearFlags": "SolidColor",
          "bgColor": [
            0.8,
            0.8,
            0.8,
            1.0
          ]
        }
      ]
    },
    {
      "name": "ScalingChoice_BlueGreen_Blue_30deg",
      "trigger": {
        "type": "time",
        "seconds": 45
      },
      "closedLoopOrientation": true,
      "closedLoopPosition": true,
      "objects": [
        {
          "type": "ScalingCylinder",
          "polar": {
            "radius": 60,
            "angle": -15.0,
            "height": 0
          },
          "material": "BlueGreen",
          "scale": {
            "x": 7,
            "y": 100,
            "z": 7
          },
          "visualAngleDegrees": 10
        },
        {
          "type": "ScalingCylinder",
          "polar": {
            "radius": 60,
            "angle": 15.0,
            "height": 0
          },
          "material": "Blue",
          "scale": {
            "x": 7,
            "y": 100,
            "z": 7
          },
          "visualAngleDegrees": 10
        }
      ],
      "camera": [
        {
          "vrId": "VR1",
          "clearFlags": "SolidColor",
          "bgColor": [
            0.8,
            0.8,
            0.8,
            1.0
          ]
        },
        {
          "vrId": "VR2",
          "clearFlags": "SolidColor",
          "bgColor": [
            0.8,
            0.8,
            0.8,
            1.0
          ]
        },
        {
          "vrId": "VR3",
          "clearFlags": "SolidColor",
          "bgColor": [
            0.8,
            0.8,
            0.8,
            1.0
          ]
        },
        {
          "vrId": "VR4",
          "clearFlags": "SolidColor",
          "bgColor": [
            0.8,
            0.8,
            0.8,
            1.0
          ]
        }
      ]
    },
    {
      "name": "ScalingChoice_Blue_BlueGreen_50deg",
      "trigger": {
        "type": "time",
        "seconds": 45
      },
      "closedLoopOrientation": true,
      "closedLoopPosition": true,
      "objects": [
        {
          "type": "ScalingCylinder",
          "polar": {
            "radius": 60,
            "angle": -25.0,
            "height": 0
          },
          "material": "Blue",
          "scale": {
            "x": 7,
            "y": 100,
            "z": 7
          },
          "visualAngleDegrees": 10
        },
        {
          "type": "ScalingCylinder",
          "polar": {
            "radius": 60,
            "angle": 25.0,
            "height": 0
          },
          "material": "BlueGreen",
          "scale": {
            "x": 7,
            "y": 100,
            "z": 7
          },
          "visualAngleDegrees": 10
        }
      ],
      "camera": [
        {
          "vrId": "VR1",
          "clearFlags": "SolidColor",
          "bgColor": [
            0.8,
            0.8,
            0.8,
            1.0
          ]
        },
        {
          "vrId": "VR2",
          "clearFlags": "SolidColor",
          "bgColor": [
            0.8,
            0.8,
            0.8,
            1.0
          ]
        },
        {
          "vrId": "VR3",
          "clearFlags": "SolidColor",
          "bgColor": [
            0.8,
            0.8,
            0.8,
            1.0
          ]
        },
        {
          "vrId": "VR4",
          "clearFlags": "SolidColor",
          "bgColor": [
            0.8,
            0.8,
            0.8,
            1.0
          ]
        }
      ]
    },
    {
      "name": "ScalingChoice_BlueGreen_Blue_50deg",
      "trigger": {
        "type": "time",
        "seconds": 45
      },
      "closedLoopOrientation": true,
      "closedLoopPosition": true,
      "objects": [
        {
          "type": "ScalingCylinder",
          "polar": {
            "radius": 60,
            "angle": -25.0,
            "height": 0
          },
          "material": "BlueGreen",
          "scale": {
            "x": 7,
            "y": 100,
            "z": 7
          },
          "visualAngleDegrees": 10
        },
        {
          "type": "ScalingCylinder",
          "polar": {
            "radius": 60,
            "angle": 25.0,
            "height": 0
          },
          "material": "Blue",
          "scale": {
            "x": 7,
            "y": 100,
            "z": 7
          },
          "visualAngleDegrees": 10
        }
      ],
      "camera": [
        {
          "vrId": "VR1",
          "clearFlags": "SolidColor",
          "bgColor": [
            0.8,
            0.8,
            0.8,
            1.0
          ]
        },
        {
          "vrId": "VR2",
          "clearFlags": "SolidColor",
          "bgColor": [
            0.8,
            0.8,
            0.8,
            1.0
          ]
        },
        {
          "vrId": "VR3",
          "clearFlags": "SolidColor",
          "bgColor": [
            0.8,
            0.8,
            0.8,
            1.0
          ]
        },
        {
          "vrId": "VR4",
          "clearFlags": "SolidColor",
          "bgColor": [
            0.8,
            0.8,
            0.8,
            1.0
          ]
        }
      ]
    },
    {
      "name": "ScalingChoice_Blue_BlueGreen_70deg",
      "trigger": {
        "type": "time",
        "seconds": 45
      },
      "closedLoopOrientation": true,
      "closedLoopPosition": true,
      "objects": [
        {
          "type": "ScalingCylinder",
          "polar": {
            "radius": 60,
            "angle": -35.0,
            "height": 0
          },
          "material": "Blue",
          "scale": {
            "x": 7,
            "y": 100,
            "z": 7
          },
          "visualAngleDegrees": 10
        },
        {
          "type": "ScalingCylinder",
          "polar": {
            "radius": 60,
            "angle": 35.0,
            "height": 0
          },
          "material": "BlueGreen",
          "scale": {
            "x": 7,
            "y": 100,
            "z": 7
          },
          "visualAngleDegrees": 10
        }
      ],
      "camera": [
        {
          "vrId": "VR1",
          "clearFlags": "SolidColor",
          "bgColor": [
            0.8,
            0.8,
            0.8,
            1.0
          ]
        },
        {
          "vrId": "VR2",
          "clearFlags": "SolidColor",
          "bgColor": [
            0.8,
            0.8,
            0.8,
            1.0
          ]
        },
        {
          "vrId": "VR3",
          "clearFlags": "SolidColor",
          "bgColor": [
            0.8,
            0.8,
            0.8,
            1.0
          ]
        },
        {
          "vrId": "VR4",
          "clearFlags": "SolidColor",
          "bgColor": [
            0.8,
            0.8,
            0.8,
            1.0
          ]
        }
      ]
    },
    {
      "name": "ScalingChoice_BlueGreen_Blue_70deg",
      "trigger": {
        "type": "time",
        "seconds": 45
      },
      "closedLoopOrientation": true,
      "closedLoopPosition": true,
      "objects": [
        {
          "type": "ScalingCylinder",
          "polar": {
            "radius": 60,
            "angle": -35.0,
            "height": 0
          },
          "material": "BlueGreen",
          "scale": {
            "x": 7,
            "y": 100,
            "z": 7
          },
          "visualAngleDegrees": 10
        },
        {
          "type": "ScalingCylinder",
          "polar": {
            "radius": 60,
            "angle": 35.0,
            "height": 0
          },
          "material": "Blue",
          "scale": {
            "x": 7,
            "y": 100,
            "z": 7
          },
          "visualAngleDegrees": 10
        }
      ],
      "camera": [
        {
          "vrId": "VR1",
          "clearFlags": "SolidColor",
          "bgColor": [
            0.8,
            0.8,
            0.8,
            1.0
          ]
        },
        {
          "vrId": "VR2",
          "clearFlags": "SolidColor",
          "bgColor": [
            0.8,
            0.8,
            0.8,
            1.0
          ]
        },
        {
          "vrId": "VR3",
          "clearFlags": "SolidColor",
          "bgColor": [
            0.8,
            0.8,
            0.8,
            1.0
          ]
        },
        {
          "vrId": "VR4",
          "clearFlags": "SolidColor",
          "bgColor": [
            0.8,
            0.8,
            0.8,
            1.0
          ]
        }
      ]
    },
    {
      "name": "ScalingChoice_Blue_BlueGreen_90deg",
      "trigger": {
        "type": "time",
        "seconds": 45
      },
      "closedLoopOrientation": true,
      "closedLoopPosition": true,
      "objects": [
        {
          "type": "ScalingCylinder",
          "polar": {
            "radius": 60,
            "angle": -45.0,
            "height": 0
          },
          "material": "Blue",
          "scale": {
            "x": 7,
            "y": 100,
            "z": 7
          },
          "visualAngleDegrees": 10
        },
        {
          "type": "ScalingCylinder",
          "polar": {
            "radius": 60,
            "angle": 45.0,
            "height": 0
          },
          "material": "BlueGreen",
          "scale": {
            "x": 7,
            "y": 100,
            "z": 7
          },
          "visualAngleDegrees": 10
        }
      ],
      "camera": [
        {
          "vrId": "VR1",
          "clearFlags": "SolidColor",
          "bgColor": [
            0.8,
            0.8,
            0.8,
            1.0
          ]
        },
        {
          "vrId": "VR2",
          "clearFlags": "SolidColor",
          "bgColor": [
            0.8,
            0.8,
            0.8,
            1.0
          ]
        },
        {
          "vrId": "VR3",
          "clearFlags": "SolidColor",
          "bgColor": [
            0.8,
            0.8,
            0.8,
            1.0
          ]
        },
        {
          "vrId": "VR4",
          "clearFlags": "SolidColor",
          "bgColor": [
            0.8,
            0.8,
            0.8,
            1.0
          ]
        }
      ]
    },
    {
      "name": "ScalingChoice_BlueGreen_Blue_90deg",
      "trigger": {
        "type": "time",
        "seconds": 45
      },
      "closedLoopOrientation": true,
      "closedLoopPosition": true,
      "objects": [
        {
          "type": "ScalingCylinder",
          "polar": {
            "radius": 60,
            "angle": -45.0,
            "height": 0
          },
          "material": "BlueGreen",
          "scale": {
            "x": 7,
            "y": 100,
            "z": 7
          },
          "visualAngleDegrees": 10
        },
        {
          "type": "ScalingCylinder",
          "polar": {
            "radius": 60,
            "angle": 45.0,
            "height": 0
          },
          "material": "Blue",
          "scale": {
            "x": 7,
            "y": 100,
            "z": 7
          },
          "visualAngleDegrees": 10
        }
      ],
      "camera": [
        {
          "vrId": "VR1",
          "clearFlags": "SolidColor",
          "bgColor": [
            0.8,
            0.8,
            0.8,
            1.0
          ]
        },
        {
          "vrId": "VR2",
          "clearFlags": "SolidColor",
          "bgColor": [
            0.8,
            0.8,
            0.8,
            1.0
          ]
        },
        {
          "vrId": "VR3",
          "clearFlags": "SolidColor",
          "bgColor": [
            0.8,
            0.8,
            0.8,
            1.0
          ]
        },
        {
          "vrId": "VR4",
          "clearFlags": "SolidColor",
          "bgColor": [
            0.8,
            0.8,
            0.8,
            1.0
          ]
        }
      ]
    },
    {
      "name": "ScalingChoice_Blue_BlueGreen_110deg",
      "trigger": {
        "type": "time",
        "seconds": 45
      },
      "closedLoopOrientation": true,
      "closedLoopPosition": true,
      "objects": [
        {
          "type": "ScalingCylinder",
          "polar": {
            "radius": 60,
            "angle": -55.0,
            "height": 0
          },
          "material": "Blue",
          "scale": {
            "x": 7,
            "y": 100,
            "z": 7
          },
          "visualAngleDegrees": 10
        },
        {
          "type": "ScalingCylinder",
          "polar": {
            "radius": 60,
            "angle": 55.0,
            "height": 0
          },
          "material": "BlueGreen",
          "scale": {
            "x": 7,
            "y": 100,
            "z": 7
          },
          "visualAngleDegrees": 10
        }
      ],
      "camera": [
        {
          "vrId": "VR1",
          "clearFlags": "SolidColor",
          "bgColor": [
            0.8,
            0.8,
            0.8,
            1.0
          ]
        },
        {
          "vrId": "VR2",
          "clearFlags": "SolidColor",
          "bgColor": [
            0.8,
            0.8,
            0.8,
            1.0
          ]
        },
        {
          "vrId": "VR3",
          "clearFlags": "SolidColor",
          "bgColor": [
            0.8,
            0.8,
            0.8,
            1.0
          ]
        },
        {
          "vrId": "VR4",
          "clearFlags": "SolidColor",
          "bgColor": [
            0.8,
            0.8,
            0.8,
            1.0
          ]
        }
      ]
    },
    {
      "name": "ScalingChoice_BlueGreen_Blue_110deg",
      "trigger": {
        "type": "time",
        "seconds": 45
      },
      "closedLoopOrientation": true,
      "closedLoopPosition": true,
      "objects": [
        {
          "type": "ScalingCylinder",
          "polar": {
            "radius": 60,
            "angle": -55.0,
            "height": 0
          },
          "material": "BlueGreen",
          "scale": {
            "x": 7,
            "y": 100,
            "z": 7
          },
          "visualAngleDegrees": 10
        },
        {
          "type": "ScalingCylinder",
          "polar": {
            "radius": 60,
            "angle": 55.0,
            "height": 0
          },
          "material": "Blue",
          "scale": {
            "x": 7,
            "y": 100,
            "z": 7
          },
          "visualAngleDegrees": 10
        }
      ],
      "camera": [
        {
          "vrId": "VR1",
          "clearFlags": "SolidColor",
          "bgColor": [
            0.8,
            0.8,
            0.8,
            1.0
          ]
        },
        {
          "vrId": "VR2",
          "clearFlags": "SolidColor",
          "bgColor": [
            0.8,
            0.8,
            0.8,
            1.0
          ]
        },
        {
          "vrId": "VR3",
          "clearFlags": "SolidColor",
          "bgColor": [
            0.8,
            0.8,
            0.8,
            1.0
          ]
        },
        {
          "vrId": "VR4",
          "clearFlags": "SolidColor",
          "bgColor": [
            0.8,
            0.8,
            0.8,
            1.0
          ]
        }
      ]
    },
    {
      "name": "ScalingChoice_Blue_BlueGreen_130deg",
      "trigger": {
        "type": "time",
        "seconds": 45
      },
      "closedLoopOrientation": true,
      "closedLoopPosition": true,
      "objects": [
        {
          "type": "ScalingCylinder",
          "polar": {
            "radius": 60,
            "angle": -65.0,
            "height": 0
          },
          "material": "Blue",
          "scale": {
            "x": 7,
            "y": 100,
            "z": 7
          },
          "visualAngleDegrees": 10
        },
        {
          "type": "ScalingCylinder",
          "polar": {
            "radius": 60,
            "angle": 65.0,
            "height": 0
          },
          "material": "BlueGreen",
          "scale": {
            "x": 7,
            "y": 100,
            "z": 7
          },
          "visualAngleDegrees": 10
        }
      ],
      "camera": [
        {
          "vrId": "VR1",
          "clearFlags": "SolidColor",
          "bgColor": [
            0.8,
            0.8,
            0.8,
            1.0
          ]
        },
        {
          "vrId": "VR2",
          "clearFlags": "SolidColor",
          "bgColor": [
            0.8,
            0.8,
            0.8,
            1.0
          ]
        },
        {
          "vrId": "VR3",
          "clearFlags": "SolidColor",
          "bgColor": [
            0.8,
            0.8,
            0.8,
            1.0
          ]
        },
        {
          "vrId": "VR4",
          "clearFlags": "SolidColor",
          "bgColor": [
            0.8,
            0.8,
            0.8,
            1.0
          ]
        }
      ]
    },
    {
      "name": "ScalingChoice_BlueGreen_Blue_130deg",
      "trigger": {
        "type": "time",
        "seconds": 45
      },
      "closedLoopOrientation": true,
      "closedLoopPosition": true,
      "objects": [
        {
          "type": "ScalingCylinder",
          "polar": {
            "radius": 60,
            "angle": -65.0,
            "height": 0
          },
          "material": "BlueGreen",
          "scale": {
            "x": 7,
            "y": 100,
            "z": 7
          },
          "visualAngleDegrees": 10
        },
        {
          "type": "ScalingCylinder",
          "polar": {
            "radius": 60,
            "angle": 65.0,
            "height": 0
          },
          "material": "Blue",
          "scale": {
            "x": 7,
            "y": 100,
            "z": 7
          },
          "visualAngleDegrees": 10
        }
      ],
      "camera": [
        {
          "vrId": "VR1",
          "clearFlags": "SolidColor",
          "bgColor": [
            0.8,
            0.8,
            0.8,
            1.0
          ]
        },
        {
          "vrId": "VR2",
          "clearFlags": "SolidColor",
          "bgColor": [
            0.8,
            0.8,
            0.8,
            1.0
          ]
        },
        {
          "vrId": "VR3",
          "clearFlags": "SolidColor",
          "bgColor": [
            0.8,
            0.8,
            0.8,
            1.0
          ]
        },
        {
          "vrId": "VR4",
          "clearFlags": "SolidColor",
          "bgColor": [
            0.8,
            0.8,
            0.8,
            1.0
          ]
        }
      ]
    },
    {
      "name": "ScalingChoice_Blue_BlueGreen_150deg",
      "trigger": {
        "type": "time",
        "seconds": 45
      },
      "closedLoopOrientation": true,
      "closedLoopPosition": true,
      "objects": [
        {
          "type": "ScalingCylinder",
          "polar": {
            "radius": 60,
            "angle": -75.0,
            "height": 0
          },
          "material": "Blue",
          "scale": {
            "x": 7,
            "y": 100,
            "z": 7
          },
          "visualAngleDegrees": 10
        },
        {
          "type": "ScalingCylinder",
          "polar": {
            "radius": 60,
            "angle": 75.0,
            "height": 0
          },
          "material": "BlueGreen",
          "scale": {
            "x": 7,
            "y": 100,
            "z": 7
          },
          "visualAngleDegrees": 10
        }
      ],
      "camera": [
        {
          "vrId": "VR1",
          "clearFlags": "SolidColor",
          "bgColor": [
            0.8,
            0.8,
            0.8,
            1.0
          ]
        },
        {
          "vrId": "VR2",
          "clearFlags": "SolidColor",
          "bgColor": [
            0.8,
            0.8,
            0.8,
            1.0
          ]
        },
        {
          "vrId": "VR3",
          "clearFlags": "SolidColor",
          "bgColor": [
            0.8,
            0.8,
            0.8,
            1.0
          ]
        },
        {
          "vrId": "VR4",
          "clearFlags": "SolidColor",
          "bgColor": [
            0.8,
            0.8,
            0.8,
            1.0
          ]
        }
      ]
    },
    {
      "name": "ScalingChoice_BlueGreen_Blue_150deg",
      "trigger": {
        "type": "time",
        "seconds": 45
      },
      "closedLoopOrientation": true,
      "closedLoopPosition": true,
      "objects": [
        {
          "type": "ScalingCylinder",
          "polar": {
            "radius": 60,
            "angle": -75.0,
            "height": 0
          },
          "material": "BlueGreen",
          "scale": {
            "x": 7,
            "y": 100,
            "z": 7
          },
          "visualAngleDegrees": 10
        },
        {
          "type": "ScalingCylinder",
          "polar": {
            "radius": 60,
            "angle": 75.0,
            "height": 0
          },
          "material": "Blue",
          "scale": {
            "x": 7,
            "y": 100,
            "z": 7
          },
          "visualAngleDegrees": 10
        }
      ],
      "camera": [
        {
          "vrId": "VR1",
          "clearFlags": "SolidColor",
          "bgColor": [
            0.8,
            0.8,
            0.8,
            1.0
          ]
        },
        {
          "vrId": "VR2",
          "clearFlags": "SolidColor",
          "bgColor": [
            0.8,
            0.8,
            0.8,
            1.0
          ]
        },
        {
          "vrId": "VR3",
          "clearFlags": "SolidColor",
          "bgColor": [
            0.8,
            0.8,
            0.8,
            1.0
          ]
        },
        {
          "vrId": "VR4",
          "clearFlags": "SolidColor",
          "bgColor": [
            0.8,
            0.8,
            0.8,
            1.0
          ]
        }
      ]
    },
    {
      "name": "ScalingChoice_Blue_BlueGreen_180deg",
      "trigger": {
        "type": "time",
        "seconds": 45
      },
      "closedLoopOrientation": true,
      "closedLoopPosition": true,
      "objects": [
        {
          "type": "ScalingCylinder",
          "polar": {
            "radius": 60,
            "angle": -90.0,
            "height": 0
          },
          "material": "Blue",
          "scale": {
            "x": 7,
            "y": 100,
            "z": 7
          },
          "visualAngleDegrees": 10
        },
        {
          "type": "ScalingCylinder",
          "polar": {
            "radius": 60,
            "angle": 90.0,
            "height": 0
          },
          "material": "BlueGreen",
          "scale": {
            "x": 7,
            "y": 100,
            "z": 7
          },
          "visualAngleDegrees": 10
        }
      ],
      "camera": [
        {
          "vrId": "VR1",
          "clearFlags": "SolidColor",
          "bgColor": [
            0.8,
            0.8,
            0.8,
            1.0
          ]
        },
        {
          "vrId": "VR2",
          "clearFlags": "SolidColor",
          "bgColor": [
            0.8,
            0.8,
            0.8,
            1.0
          ]
        },
        {
          "vrId": "VR3",
          "clearFlags": "SolidColor",
          "bgColor": [
            0.8,
            0.8,
            0.8,
            1.0
          ]
        },
        {
          "vrId": "VR4",
          "clearFlags": "SolidColor",
          "bgColor": [
            0.8,
            0.8,
            0.8,
            1.0
          ]
        }
      ]
    },
    {
      "name": "ScalingChoice_BlueGreen_Blue_180deg",
      "trigger": {
        "type": "time",
        "seconds": 45
      },
      "closedLoopOrientation": true,
      "closedLoopPosition": true,
      "objects": [
        {
          "type": "ScalingCylinder",
          "polar": {
            "radius": 60,
            "angle": -90.0,
            "height": 0
          },
          "material": "BlueGreen",
          "scale": {
            "x": 7,
            "y": 100,
            "z": 7
          },
          "visualAngleDegrees": 10
        },
        {
          "type": "ScalingCylinder",
          "polar": {
            "radius": 60,
            "angle": 90.0,
            "height": 0
          },
          "material": "Blue",
          "scale": {
            "x": 7,
            "y": 100,
            "z": 7
          },
          "visualAngleDegrees": 10
        }
      ],
      "camera": [
        {
          "vrId": "VR1",
          "clearFlags": "SolidColor",
          "bgColor": [
            0.8,
            0.8,
            0.8,
            1.0
          ]
        },
        {
          "vrId": "VR2",
          "clearFlags": "SolidColor",
          "bgColor": [
            0.8,
            0.8,
            0.8,
            1.0
          ]
        },
        {
          "vrId": "VR3",
          "clearFlags": "SolidColor",
          "bgColor": [
            0.8,
            0.8,
            0.8,
            1.0
          ]
        },
        {
          "vrId": "VR4",
          "clearFlags": "SolidColor",
          "bgColor": [
            0.8,
            0.8,
            0.8,
            1.0
          ]
        }
      ]
    }
  ]
}