{
  "objects": [
    {
      "type": "cylinder",
      "position": {
        "radius": 30,
        "angle": 15
      },
      "material": "white",
      "scale": {
        "x": 8,
        "y": 17,
        "z": 8
      }
    },
    {
      "type": "cylinder",
      "position": {
        "radius": 30,
        "angle": 345
      },
      "material": "white",
      "scale": {
        "x": 8,
        "y": 17,
        "z": 8
      }
    }
  ],
  "closedLoopOrientation": true,
  "closedLoopPosition": false,
  "backgroundColor": {
    "r": 0,
    "g": 0,
    "b": 0,
    "a": 1
  }
}